authority/__init__.py
authority/admin.py
authority/decorators.py
authority/exceptions.py
authority/forms.py
authority/managers.py
authority/models.py
authority/permissions.py
authority/sites.py
authority/tests.py
authority/urls.py
authority/utils.py
authority/views.py
authority/widgets.py
authority/fixtures/tests_custom.json
authority/migrations/0001_initial.py
authority/migrations/__init__.py
authority/templates/admin/permission_change_form.html
authority/templates/admin/edit_inline/action_tabular.html
authority/templates/authority/403.html
authority/templates/authority/permission_delete_link.html
authority/templates/authority/permission_form.html
authority/templates/authority/permission_request_approve_link.html
authority/templates/authority/permission_request_delete_link.html
authority/templatetags/__init__.py
authority/templatetags/permissions.py
django_authority-0.14.dist-info/AUTHORS
django_authority-0.14.dist-info/LICENSE
django_authority-0.14.dist-info/METADATA
django_authority-0.14.dist-info/WHEEL
django_authority-0.14.dist-info/top_level.txt
django_authority-0.14.dist-info/RECORD
