Metadata-Version: 2.1
Name: django-authority
Version: 0.14
Summary: A Django app that provides generic per-object-permissions for Django's auth app.
Home-page: https://github.com/jazzband/django-authority/
Author: Jannis Leidel
Author-email: jannis@leidel.info
License: BSD
Platform: UNKNOWN
Classifier: Development Status :: 5 - Production/Stable
Classifier: Environment :: Web Environment
Classifier: Intended Audience :: Developers
Classifier: License :: OSI Approved :: BSD License
Classifier: Operating System :: OS Independent
Classifier: Programming Language :: Python
Classifier: Programming Language :: Python :: 2
Classifier: Programming Language :: Python :: 2.7
Classifier: Programming Language :: Python :: 3
Classifier: Programming Language :: Python :: 3.7
Classifier: Framework :: Django
